LICENSE
configmate/__init__.py
configmate/base/__init__.py
configmate/base/constants.py
configmate/base/exceptions.py
configmate/base/operators.py
configmate/base/registry.py
configmate/base/types.py
configmate/components/__init__.py
configmate/components/aggregators.py
configmate/components/cli_readers.py
configmate/components/filereader.py
configmate/components/interpolators.py
configmate/components/parsers.py
configmate/components/selectors.py
configmate/components/validators.py
configmate/core/__init__.py
configmate/core/builders.py
configmate/core/composers.py
configmate/core/functions.py
configmate/py.typed
configmate-0.1.8.dist-info/LICENSE
configmate-0.1.8.dist-info/METADATA
configmate-0.1.8.dist-info/WHEEL
configmate-0.1.8.dist-info/RECORD
