Metadata-Version: 2.1
Name: configmate
Version: 0.1.8
Summary: Practical and versatile configuration parsing in Python.
License: Apache 2.0
Keywords: configuration,config,parser,config-parser
Author: Arthur Böök
Requires-Python: >=3.8,<4.0
Classifier: License :: Other/Proprietary License
Classifier: Programming Language :: Python :: 3
Classifier: Programming Language :: Python :: 3.8
Classifier: Programming Language :: Python :: 3.9
Classifier: Programming Language :: Python :: 3.10
Classifier: Programming Language :: Python :: 3.11
Classifier: Programming Language :: Python :: 3.12
Provides-Extra: pydantic
Provides-Extra: standard
Provides-Extra: toml
Provides-Extra: yaml
Requires-Dist: configmate-pydantic-validator (>=0.1.0,<0.2.0) ; extra == "standard" or extra == "pydantic"
Requires-Dist: configmate-tomlparser ; extra == "toml"
Requires-Dist: configmate-yamlparser ; extra == "standard" or extra == "yaml"
Project-URL: repository, https://github.com/ArthurBook/configmate
